{
    "$schema": "http://json-schema.org/draft-04/schema#",
    "type": "object",
    "additionalProperties": false,
    "properties": {
      "categoryId": {
        "type": "string"
      },
      "dimensions": {
        "type": "object"
      },
      "name": {
        "type": "string"
      },
      "variations": {
        "type": "array",
        "items": {
          "type": "object"
        }
      },
      "palette": {
        "type": "array",
        "items": {
          "type": "object"
        }
      },
      "tags": {
        "type": "array",
        "items": {
          "type": "string"
        }
      },
      "dateCreated": {
        "type": "string"
      },
      "usageCount": {
        "type": "number"
      }     
    }
  }
  